abstract_gui/RightClickManager.py
abstract_gui/SimpleGuiFunctionsManager.py
abstract_gui/__init__.py
abstract_gui/abstract_browser.py
abstract_gui/abstract_gui.py
abstract_gui/abstract_next_read_manager.py
abstract_gui/abstract_window_global_bridge.py
abstract_gui/abstract_window_manager.py
abstract_gui/main.py
abstract_gui/right_click_test.py
abstract_gui/QT5/__init__.py
abstract_gui/QT5/gui_components.py
abstract_gui/QT5/gui_utils.py
abstract_gui/QT5/managers/__init__.py
abstract_gui/QT5/managers/inputDialog.py
abstract_gui/QT5/managers/winSys.py
abstract_gui/QT5/managers/window_info_gui.py
abstract_gui/QT5/widgets/__init__.py
abstract_gui/QT5/widgets/imports/__init__.py
abstract_gui/QT5/widgets/imports/imports.py
abstract_gui/QT5/widgets/utils/__init__.py
abstract_gui/QT5/widgets/utils/kwargs_utils.py
abstract_gui/QT5/widgets/utils/utils.py
abstract_gui/QT5/widgets/utils/widgets.py
abstract_gui/QT6/__init__.py
abstract_gui/QT6/factories/__init__.py
abstract_gui/QT6/factories/abstract_visibility.py
abstract_gui/QT6/factories/auto_signals.py
abstract_gui/QT6/factories/constants.py
abstract_gui/QT6/factories/properties_resolver.py
abstract_gui/QT6/factories/registry_resolver.py
abstract_gui/QT6/factories/signal_registry.py
abstract_gui/QT6/factories/tableFactory.py
abstract_gui/QT6/factories/table_factory_headers_config.py
abstract_gui/QT6/functions/__init__.py
abstract_gui/QT6/functions/imports.py
abstract_gui/QT6/functions/combos/__init__.py
abstract_gui/QT6/functions/combos/imports.py
abstract_gui/QT6/functions/combos/utils/__init__.py
abstract_gui/QT6/functions/combos/utils/linked_combos.py
abstract_gui/QT6/imports/QT6_imports.py
abstract_gui/QT6/imports/__init__.py
abstract_gui/QT6/imports/abstract_utils.py
abstract_gui/QT6/imports/constants.py
abstract_gui/QT6/imports/functions.py
abstract_gui/QT6/imports/general_imports.py
abstract_gui/QT6/imports/imports.py
abstract_gui/QT6/imports/pathsimports.py
abstract_gui/QT6/imports/utils.py
abstract_gui-0.1.63.221.dist-info/METADATA
abstract_gui-0.1.63.221.dist-info/WHEEL
abstract_gui-0.1.63.221.dist-info/top_level.txt
abstract_gui-0.1.63.221.dist-info/RECORD
