Metadata-Version: 2.4
Name: abstract_gui
Version: 0.1.63.221
Summary: abstract_gui provides reusable components, factories, utilities for logging, threading, state management, and more, making it easier to build responsive, feature-rich interfaces without boilerplate code.
Home-page: https://github.com/AbstractEndeavors/abstract_gui
Author: putkoff
Author-email: partners@abstractendeavors.com
Classifier: Development Status :: 3 - Alpha
Classifier: Intended Audience :: Developers
Classifier: License :: OSI Approved :: MIT License
Classifier: Programming Language :: Python :: 3
Classifier: Programming Language :: Python :: 3.11
Requires-Python: >=3.6
Requires-Dist: abstract_utilities
Requires-Dist: PySimpleGUIWeb
Requires-Dist: PySimpleGUI
Dynamic: author
Dynamic: author-email
Dynamic: classifier
Dynamic: description
Dynamic: description-content-type
Dynamic: home-page
Dynamic: requires-dist
Dynamic: requires-python
Dynamic: summary
